setup.cfg
setup.py
ypya/__init__.py
ypya/__version__.py
ypya/base.py
ypya/payload.py
ypya/transport.py
ypya/utils.py
ypya.egg-info/PKG-INFO
ypya.egg-info/SOURCES.txt
ypya.egg-info/dependency_links.txt
ypya.egg-info/requires.txt
ypya.egg-info/top_level.txt