Metadata-Version: 1.2
Name: ypya
Version: 1.3.3
Summary: simple logging handler with AMQP and GELF
Home-page: http://rcs.studio.home/project/ypya
Author: "Xingeng Chen"
Author-email: cxg@studio.home
License: Apache License 2.0
Platform: UNKNOWN
Classifier: Development Status :: 4 - Beta
Classifier: Intended Audience :: Developers
Classifier: License :: OSI Approved :: Apache Software License
Classifier: Operating System :: OS Independent
Classifier: Programming Language :: Python
Classifier: Programming Language :: Python :: 2.7
Classifier: Programming Language :: Python :: 3.7
Classifier: Programming Language :: Python :: 3.8
Classifier: Programming Language :: Python :: 3.9
Requires-Python: >=2.7
